bilibili_api/__init__.py
bilibili_api/activity.py
bilibili_api/app.py
bilibili_api/article.py
bilibili_api/article_category.py
bilibili_api/ass.py
bilibili_api/audio.py
bilibili_api/audio_uploader.py
bilibili_api/bangumi.py
bilibili_api/black_room.py
bilibili_api/channel_series.py
bilibili_api/cheese.py
bilibili_api/client.py
bilibili_api/comment.py
bilibili_api/creative_center.py
bilibili_api/dynamic.py
bilibili_api/emoji.py
bilibili_api/favorite_list.py
bilibili_api/festival.py
bilibili_api/game.py
bilibili_api/garb.py
bilibili_api/homepage.py
bilibili_api/hot.py
bilibili_api/interactive_video.py
bilibili_api/live.py
bilibili_api/live_area.py
bilibili_api/login_v2.py
bilibili_api/manga.py
bilibili_api/music.py
bilibili_api/note.py
bilibili_api/opus.py
bilibili_api/py.typed
bilibili_api/rank.py
bilibili_api/search.py
bilibili_api/session.py
bilibili_api/show.py
bilibili_api/topic.py
bilibili_api/user.py
bilibili_api/video.py
bilibili_api/video_tag.py
bilibili_api/video_uploader.py
bilibili_api/video_zone.py
bilibili_api/vote.py
bilibili_api/watchroom.py
bilibili_api/_pyinstaller/entry_points.py
bilibili_api/_pyinstaller/hook-bilibili_api.py
bilibili_api/clients/AioHTTPClient.py
bilibili_api/clients/CurlCFFIClient.py
bilibili_api/clients/HTTPXClient.py
bilibili_api/clients/__init__.py
bilibili_api/data/appeal.json
bilibili_api/data/article_category.json
bilibili_api/data/audio_search_tags.json
bilibili_api/data/bangumi_index_params.json
bilibili_api/data/browser_fingerprint.json
bilibili_api/data/countries_codes.json
bilibili_api/data/subtitle_lan.json
bilibili_api/data/video_uploader_lines.json
bilibili_api/data/video_uploader_meta_pre.json
bilibili_api/data/video_zone.json
bilibili_api/data/api/README.md
bilibili_api/data/api/activity.json
bilibili_api/data/api/album.json
bilibili_api/data/api/app.json
bilibili_api/data/api/article-category.json
bilibili_api/data/api/article.json
bilibili_api/data/api/audio.json
bilibili_api/data/api/audio_uploader.json
bilibili_api_dev-18.0.0a0.dist-info/licenses/LICENSE
bilibili_api_dev-18.0.0a0.dist-info/METADATA
bilibili_api_dev-18.0.0a0.dist-info/WHEEL
bilibili_api_dev-18.0.0a0.dist-info/entry_points.txt
bilibili_api_dev-18.0.0a0.dist-info/top_level.txt
bilibili_api_dev-18.0.0a0.dist-info/RECORD
