Metadata-Version: 2.4
Name: bilibili-api-dev
Version: 18.0.0a0
Summary: The fork of module bilibili-api. 哔哩哔哩的各种 API 调用便捷整合（视频、动态、直播等），另外附加一些常用的功能。
Author-email: Nemo2011 <yimoxia@outlook.com>
Maintainer: MoyuScript, Nemo2011
License: GPL-3.0-or-later
Project-URL: Homepage, https://github.com/Nemo2011/bilibili-api
Project-URL: Repository, https://github.com/Nemo2011/bilibili-api
Project-URL: Documentation, https://nemo2011.github.io/bilibili-api
Project-URL: Bug Report, https://github.com/Nemo2011/bilibili-api/issues
Keywords: bilibili,api,spider
Classifier: Development Status :: 3 - Alpha
Classifier: License :: OSI Approved :: GNU General Public License v3 or later (GPLv3+)
Classifier: Natural Language :: Chinese (Simplified)
Classifier: Programming Language :: Python :: 3.10
Classifier: Programming Language :: Python :: 3.11
Classifier: Programming Language :: Python :: 3.12
Classifier: Programming Language :: Python :: 3.13
Classifier: Programming Language :: Python :: 3.14
Requires-Python: >=3.10
License-File: LICENSE
Requires-Dist: beautifulsoup4
Requires-Dist: colorama
Requires-Dist: lxml
Requires-Dist: pyyaml
Requires-Dist: brotli
Requires-Dist: qrcode
Requires-Dist: APScheduler
Requires-Dist: pillow
Requires-Dist: yarl
Requires-Dist: pycryptodomex
Requires-Dist: qrcode_terminal
Requires-Dist: PyJWT
Requires-Dist: anyio
Requires-Dist: frozendict
Provides-Extra: fingerprint
Requires-Dist: fpgen>=1.3.0; extra == "fingerprint"
Requires-Dist: curl-cffi>=0.13.0; extra == "fingerprint"
Dynamic: license-file
